shot_scraper/__init__.py
shot_scraper/cli.py
shot_scraper/utils.py
shot_scraper-1.9.dist-info/WHEEL
shot_scraper-1.9.dist-info/entry_points.txt
shot_scraper-1.9.dist-info/METADATA
shot_scraper-1.9.dist-info/RECORD
